input_util/__init__.py
input_util/cli.py
input_util/input_util.py
input_util-0.1.2.dist-info/WHEEL
input_util-0.1.2.dist-info/METADATA
input_util-0.1.2.dist-info/RECORD
