Metadata-Version: 2.1
Name: input-util
Version: 0.1.2
Summary: 
Author: Eyal Levin
Author-email: eyalev@gmail.com
Requires-Python: >=3.6,<4.0
Classifier: Programming Language :: Python :: 3
Classifier: Programming Language :: Python :: 3.6
Classifier: Programming Language :: Python :: 3.7
Classifier: Programming Language :: Python :: 3.8
Requires-Dist: click (>=7.1.2,<8.0.0)
Requires-Dist: file-util (>=0.1.6,<0.2.0)
Requires-Dist: is-url (>=0.1.2,<0.2.0)
